flake8_prettycount/__init__.py
flake8_prettycount/__main__.py
flake8_prettycount/application.py
flake8_prettycount/py.typed
flake8_prettycount-0.1.2.dist-info/LICENSE
flake8_prettycount-0.1.2.dist-info/METADATA
flake8_prettycount-0.1.2.dist-info/WHEEL
flake8_prettycount-0.1.2.dist-info/entry_points.txt
flake8_prettycount-0.1.2.dist-info/RECORD
