Metadata-Version: 2.1
Name: flake8-prettycount
Version: 0.1.2
Summary: Wrapper around flake8 providing a formatted count at the end.
Author-email: Dominic Davis-Foster <dominic@davis-foster.co.uk>
License: MIT
Keywords: flake8
Home-page: https://github.com/python-formate/flake8-prettycount
Project-URL: Issue Tracker, https://github.com/python-formate/flake8-prettycount/issues
Project-URL: Source Code, https://github.com/python-formate/flake8-prettycount
Platform: Windows
Platform: macOS
Platform: Linux
Classifier: Environment :: Console
Classifier: Framework :: Flake8
Classifier: Intended Audience :: Developers
Classifier: License :: OSI Approved :: MIT License
Classifier: Operating System :: OS Independent
Classifier: Programming Language :: Python
Classifier: Programming Language :: Python :: 3 :: Only
Classifier: Programming Language :: Python :: 3.6
Classifier: Programming Language :: Python :: 3.7
Classifier: Programming Language :: Python :: 3.8
Classifier: Programming Language :: Python :: 3.9
Classifier: Programming Language :: Python :: 3.10
Classifier: Programming Language :: Python :: 3.11
Classifier: Programming Language :: Python :: 3.12
Classifier: Programming Language :: Python :: Implementation :: CPython
Classifier: Programming Language :: Python :: Implementation :: PyPy
Classifier: Typing :: Typed
Requires-Python: >=3.6
Requires-Dist: click>=7.1.2
Requires-Dist: consolekit>=0.8.0
Requires-Dist: domdf-python-tools>=3.0.0
Requires-Dist: flake8>=3.8.4
Requires-Dist: typing-extensions>=3.7.4.3
